odoo/addons/__init__.py
odoo/addons/website_event_sale/__init__.py
odoo/addons/website_event_sale/__manifest__.py
odoo/addons/website_event_sale/controllers/__init__.py
odoo/addons/website_event_sale/controllers/main.py
odoo/addons/website_event_sale/data/event_data.xml
odoo/addons/website_event_sale/i18n/af.po
odoo/addons/website_event_sale/i18n/am.po
odoo/addons/website_event_sale/i18n/ar.po
odoo/addons/website_event_sale/i18n/bg.po
odoo/addons/website_event_sale/i18n/bs.po
odoo/addons/website_event_sale/i18n/ca.po
odoo/addons/website_event_sale/i18n/cs.po
odoo/addons/website_event_sale/i18n/da.po
odoo/addons/website_event_sale/i18n/de.po
odoo/addons/website_event_sale/i18n/el.po
odoo/addons/website_event_sale/i18n/en_GB.po
odoo/addons/website_event_sale/i18n/es.po
odoo/addons/website_event_sale/i18n/es_BO.po
odoo/addons/website_event_sale/i18n/es_CL.po
odoo/addons/website_event_sale/i18n/es_CO.po
odoo/addons/website_event_sale/i18n/es_CR.po
odoo/addons/website_event_sale/i18n/es_DO.po
odoo/addons/website_event_sale/i18n/es_EC.po
odoo/addons/website_event_sale/i18n/es_PA.po
odoo/addons/website_event_sale/i18n/es_PE.po
odoo/addons/website_event_sale/i18n/es_PY.po
odoo/addons/website_event_sale/i18n/es_VE.po
odoo/addons/website_event_sale/i18n/et.po
odoo/addons/website_event_sale/i18n/eu.po
odoo/addons/website_event_sale/i18n/fa.po
odoo/addons/website_event_sale/i18n/fi.po
odoo/addons/website_event_sale/i18n/fo.po
odoo/addons/website_event_sale/i18n/fr.po
odoo/addons/website_event_sale/i18n/fr_CA.po
odoo/addons/website_event_sale/i18n/gl.po
odoo/addons/website_event_sale/i18n/gu.po
odoo/addons/website_event_sale/i18n/he.po
odoo/addons/website_event_sale/i18n/hr.po
odoo/addons/website_event_sale/i18n/hu.po
odoo/addons/website_event_sale/i18n/id.po
odoo/addons/website_event_sale/i18n/is.po
odoo/addons/website_event_sale/i18n/it.po
odoo/addons/website_event_sale/i18n/ja.po
odoo/addons/website_event_sale/i18n/ka.po
odoo/addons/website_event_sale/i18n/kab.po
odooku_odoo_website_sale-11.0.7.dist-info/LICENSE
odooku_odoo_website_sale-11.0.7.dist-info/METADATA
odooku_odoo_website_sale-11.0.7.dist-info/WHEEL
odooku_odoo_website_sale-11.0.7.dist-info/top_level.txt
odooku_odoo_website_sale-11.0.7.dist-info/RECORD
